mindchemistry/__init__.py
mindchemistry/setup.py
mindchemistry/cell/__init__.py
mindchemistry/cell/activation.py
mindchemistry/cell/basic_block.py
mindchemistry/cell/convolution.py
mindchemistry/cell/cspnet.py
mindchemistry/cell/embedding.py
mindchemistry/cell/message_passing.py
mindchemistry/cell/nequip.py
mindchemistry/cell/allegro/__init__.py
mindchemistry/cell/allegro/allegro.py
mindchemistry/cell/allegro/strided/__init__.py
mindchemistry/cell/allegro/strided/channels.py
mindchemistry/cell/allegro/strided/contract.py
mindchemistry/cell/allegro/strided/layout.py
mindchemistry/cell/allegro/strided/linear.py
mindchemistry/cell/deephe3nn/__init__.py
mindchemistry/cell/deephe3nn/e3modules.py
mindchemistry/cell/deephe3nn/model.py
mindchemistry/cell/deephe3nn/utils.py
mindchemistry/cell/dimenet/__init__.py
mindchemistry/cell/dimenet/dimenet.py
mindchemistry/cell/dimenet/dimenet_utils.py
mindchemistry/cell/dimenet/dimenet_wrap.py
mindchemistry/cell/dimenet/glorot_orthogonal.py
mindchemistry/cell/dimenet/preprocess.py
mindchemistry/cell/gemnet/__init__.py
mindchemistry/cell/gemnet/data_utils.py
mindchemistry/cell/gemnet/gemnet.py
mindchemistry/cell/gemnet/gemnet_wrap.py
mindchemistry/cell/gemnet/preprocess.py
mindchemistry/cell/gemnet/utils.py
mindchemistry/cell/gemnet/layers/__init__.py
mindchemistry/cell/gemnet/layers/atom_update_block.py
mindchemistry/cell/gemnet/layers/base_layers.py
mindchemistry/cell/gemnet/layers/efficient.py
mindchemistry/cell/gemnet/layers/embedding_block.py
mindchemistry/cell/gemnet/layers/he_orthogonal.py
mindchemistry/cell/gemnet/layers/interaction_block.py
mindchemistry/cell/gemnet/layers/radial_basis.py
mindchemistry/cell/gemnet/layers/spherical_basis.py
mindchemistry/cell/matformer/__init__.py
mindchemistry/cell/matformer/matformer.py
mindchemistry/cell/matformer/transformer.py
mindchemistry/cell/matformer/utils.py
mindchemistry/e3/__init__.py
mindchemistry/e3/nn/__init__.py
mindchemistry/e3/nn/activation.py
mindchemistry_ascend-0.2.0.dist-info/METADATA
mindchemistry_ascend-0.2.0.dist-info/WHEEL
mindchemistry_ascend-0.2.0.dist-info/top_level.txt
mindchemistry_ascend-0.2.0.dist-info/RECORD
