Metadata-Version: 2.4
Name: mindchemistry_ascend
Version: 0.2.0
Summary: An AI framework for chemistry simulation
Home-page: https://www.mindspore.cn/
Download-URL: https://gitee.com/mindspore/mindscience/tags
Author: The MindSpore Authors
Author-email: contact@mindspore.cn
License: Apache 2.0
Project-URL: Sources, https://gitee.com/mindspore/mindscience
Project-URL: Issue Tracker, https://gitee.com/mindspore/mindscience/issues
Classifier: License :: OSI Approved :: Apache Software License
Requires-Dist: numpy>=1.21.6
Requires-Dist: scipy>=1.9.0
Requires-Dist: matplotlib>=3.5.3
Requires-Dist: psutil>=5.9.4
Requires-Dist: pandas>=1.3.5
Requires-Dist: scikit-learn>=1.0.2
Requires-Dist: lightgbm>=3.3.5
Requires-Dist: joblib>=1.2.0
Requires-Dist: seaborn>=0.12.2
Requires-Dist: pyyaml>=6.0
Dynamic: author
Dynamic: author-email
Dynamic: classifier
Dynamic: download-url
Dynamic: home-page
Dynamic: license
Dynamic: project-url
Dynamic: requires-dist
Dynamic: summary
